LICENSE
README.md
pyproject.toml
setup.py
fastapi_uuidbase62.egg-info/PKG-INFO
fastapi_uuidbase62.egg-info/SOURCES.txt
fastapi_uuidbase62.egg-info/dependency_links.txt
fastapi_uuidbase62.egg-info/requires.txt
fastapi_uuidbase62.egg-info/top_level.txt
uuidbase62/__init__.py
uuidbase62/base62.py
uuidbase62/dependencies.py
uuidbase62/exceptions.py
uuidbase62/models.py
uuidbase62/types.py