Metadata-Version: 2.1
Name: fastapi-uuidbase62
Version: 0.2
Summary: Leverage Stripe-formatted IDs for internal UUID values in your Pydantic models and FastAPI views; automatically validates prefixes, and converts to/from UUID values.
Home-page: https://github.com/jaddison/fastapi-uuidbase62
Author: James Addison
Author-email: addi00@gmail.com
License: UNKNOWN
Project-URL: Documentation, https://github.com/jaddison/fastapi-uuidbase62
Project-URL: Say Thanks!, https://github.com/jaddison/fastapi-uuidbase62/issues
Project-URL: Source, https://github.com/jaddison/fastapi-uuidbase62
Project-URL: Tracker, https://github.com/jaddison/fastapi-uuidbase62/issues
Keywords: stripe uuid base62 fastapi pydantic serialize
Platform: UNKNOWN
Classifier: Development Status :: 3 - Alpha
Classifier: Environment :: Web Environment
Classifier: Framework :: FastAPI
Classifier: Intended Audience :: Developers
Classifier: License :: OSI Approved :: MIT License
Classifier: Programming Language :: Python :: 3
Classifier: Programming Language :: Python :: 3.7
Classifier: Programming Language :: Python :: 3.8
Classifier: Programming Language :: Python :: 3.9
Classifier: Programming Language :: Python :: 3.10
Classifier: Programming Language :: Python :: 3.11
Classifier: Topic :: Internet :: WWW/HTTP :: HTTP Servers
Requires-Python: >=3.7, <4
License-File: LICENSE
